chanter/__init__.py
chanter/galaxy_fitter.py
chanter/model_galaxy.py
chanter/grids/__init__.py
chanter/utils/__init__.py
chanter/utils/filter_set.py
chanter/utils/make_igm_grid.py
chanter-0.0.9.dist-info/METADATA
chanter-0.0.9.dist-info/WHEEL
chanter-0.0.9.dist-info/top_level.txt
chanter-0.0.9.dist-info/RECORD
