Metadata-Version: 2.4
Name: chanter
Version: 0.0.9
Summary: Simple galaxy spectral modelling and fitting
Author: Struan Stevenson
Author-email: struan.stevenson@ed.ac.uk
Requires-Dist: numpy
Requires-Dist: astropy
Requires-Dist: matplotlib
Requires-Dist: spectres
Requires-Dist: nautilus-sampler
Dynamic: author
Dynamic: author-email
Dynamic: description
Dynamic: description-content-type
Dynamic: requires-dist
Dynamic: summary
